[
    {
        "timestamp": "2026-01-11T10:20:32.856224",
        "balance": 41753.0
    },
    {
        "timestamp": "2026-01-11T10:21:25.747505",
        "balance": 74657.92
    },
    {
        "timestamp": "2026-01-11T10:22:33.025090",
        "balance": 74238.37
    },
    {
        "timestamp": "2026-01-11T10:23:43.424954",
        "balance": 74221.06
    },
    {
        "timestamp": "2026-01-11T10:24:03.736096",
        "balance": 74165.96
    },
    {
        "timestamp": "2026-01-11T10:24:48.713701",
        "balance": 74166.35
    },
    {
        "timestamp": "2026-01-11T10:25:37.686456",
        "balance": 74094.47
    },
    {
        "timestamp": "2026-01-11T10:26:34.319658",
        "balance": 73969.93
    },
    {
        "timestamp": "2026-01-11T10:27:54.064579",
        "balance": 73959.36
    },
    {
        "timestamp": "2026-01-11T11:38:35.045385",
        "balance": 73548.86
    },
    {
        "timestamp": "2026-01-11T11:48:26.033303",
        "balance": 73726.93
    },
    {
        "timestamp": "2026-01-11T12:02:24.709801",
        "balance": 72789.34
    },
    {
        "timestamp": "2026-01-11T12:04:24.738490",
        "balance": 72454.22
    },
    {
        "timestamp": "2026-01-11T12:06:57.563944",
        "balance": 72654.52
    },
    {
        "timestamp": "2026-01-11T12:11:43.191803",
        "balance": 72262.95
    },
    {
        "timestamp": "2026-01-11T12:43:53.402690",
        "balance": 71736.27
    },
    {
        "timestamp": "2026-01-11T12:47:12.112585",
        "balance": 71546.6
    },
    {
        "timestamp": "2026-01-11T13:04:02.523404",
        "balance": 71383.3
    },
    {
        "timestamp": "2026-01-11T13:07:01.719094",
        "balance": 71383.3
    }
]